setup.py
GBZQ_distributions.egg-info/PKG-INFO
GBZQ_distributions.egg-info/SOURCES.txt
GBZQ_distributions.egg-info/dependency_links.txt
GBZQ_distributions.egg-info/not-zip-safe
GBZQ_distributions.egg-info/top_level.txt
distributions/Binomialdistribution.py
distributions/Gaussiandistribution.py
distributions/Generaldistribution.py
distributions/__init__.py